bifacial_radiance/__init__.py
bifacial_radiance/gui.py
bifacial_radiance/load.py
bifacial_radiance/main.py
bifacial_radiance/mismatch.py
bifacial_radiance/modelchain.py
bifacial_radiance/module.py
bifacial_radiance/performance.py
bifacial_radiance/spectral_utils.py
bifacial_radiance/HPCScripts/BasicSimulations/addNewModule.py
bifacial_radiance/HPCScripts/BasicSimulations/dask_on_node.sh
bifacial_radiance/HPCScripts/BasicSimulations/run_sbatch.sbatch
bifacial_radiance/HPCScripts/BasicSimulations/simulate_fixedtilt_gencumsky.py
bifacial_radiance/HPCScripts/BasicSimulations/simulate_fixedtilt_gendaylit.py
bifacial_radiance/HPCScripts/BasicSimulations/simulate_tracking_gendaylit.py
bifacial_radiance/HPCScripts/Other Examples (unorganized)/PuertoRico.py
bifacial_radiance/HPCScripts/Other Examples (unorganized)/PuertoRico_2.py
bifacial_radiance/HPCScripts/Other Examples (unorganized)/PuertoRico_Original.py
bifacial_radiance/HPCScripts/Other Examples (unorganized)/basic_module_sampling.py
bifacial_radiance/HPCScripts/Other Examples (unorganized)/compile_B.py
bifacial_radiance/HPCScripts/Other Examples (unorganized)/compile_Cases.py
bifacial_radiance/HPCScripts/Other Examples (unorganized)/compile_CasesMonth.py
bifacial_radiance/HPCScripts/Other Examples (unorganized)/compile_PRNew.py
bifacial_radiance/HPCScripts/Other Examples (unorganized)/compile_PRNewP2.py
bifacial_radiance/HPCScripts/Other Examples (unorganized)/compile_TreeResults.py
bifacial_radiance/HPCScripts/Other Examples (unorganized)/compile_basic_module_sampling.py
bifacial_radiance/HPCScripts/Other Examples (unorganized)/simulate_JackHourly.py
bifacial_radiance/HPCScripts/Other Examples (unorganized)/simulate_improvedArray_Oct2127.py
bifacial_radiance/TEMP/.gitignore
bifacial_radiance/data/CEC Modules.csv
bifacial_radiance/data/default.ini
bifacial_radiance/data/falsecolor.exe
bifacial_radiance/data/gencumsky.exe
bifacial_radiance/data/gencumulativesky
bifacial_radiance/data/gencumulativesky.exe
bifacial_radiance-0.5.0.dist-info/licenses/LICENSE
bifacial_radiance-0.5.0.dist-info/METADATA
bifacial_radiance-0.5.0.dist-info/WHEEL
bifacial_radiance-0.5.0.dist-info/top_level.txt
bifacial_radiance-0.5.0.dist-info/RECORD
