Metadata-Version: 2.4
Name: bifacial_radiance
Version: 0.5.0
Summary: Tools to interface with Radiance for the PV researcher
Author-email: Chris Deline <chris.deline@nrel.gov>, Silvana Ovaitt <silvana.ovaitt@nrel.gov>
Project-URL: Homepage, https://github.com/NREL/bifacial_radiance
Project-URL: Documentation, https://bifacial-radiance.readthedocs.io
Project-URL: Repository, https://github.com/NREL/bifacial_radiance
Project-URL: Issues, https://github.com/NREL/bifacial_radiance/issues
Keywords: bifacial,radiance,photovoltaics,pv,ray tracing
Classifier: Development Status :: 4 - Beta
Classifier: Intended Audience :: Science/Research
Classifier: License :: OSI Approved :: BSD License
Classifier: Programming Language :: Python :: 3
Classifier: Programming Language :: Python :: 3.8
Classifier: Programming Language :: Python :: 3.9
Classifier: Programming Language :: Python :: 3.10
Classifier: Programming Language :: Python :: 3.11
Classifier: Programming Language :: Python :: 3.12
Classifier: Programming Language :: Python :: 3.13
Requires-Python: >=3.8
License-File: LICENSE
Requires-Dist: configparser
Requires-Dist: deprecated
Requires-Dist: pandas
Requires-Dist: pvlib>=0.8.0
Requires-Dist: pvmismatch
Requires-Dist: pyradiance
Requires-Dist: requests
Requires-Dist: scipy>1.6.0
Requires-Dist: tqdm
Provides-Extra: test
Requires-Dist: pytest; extra == "test"
Requires-Dist: pytest-cov; extra == "test"
Requires-Dist: pySMARTS; extra == "test"
Provides-Extra: doc
Requires-Dist: ipython; extra == "doc"
Requires-Dist: sphinx>=1.8.0; extra == "doc"
Requires-Dist: sphinx-autoapi>=1.1.0; extra == "doc"
Requires-Dist: pydata-sphinx-theme>=0.14.4; extra == "doc"
Requires-Dist: nbsphinx>=0.8.8; extra == "doc"
Requires-Dist: sphinx-gallery>=0.8.1; extra == "doc"
Provides-Extra: all
Requires-Dist: bifacial_radiance[doc,test]; extra == "all"
Requires-Dist: jupyter; extra == "all"
Dynamic: license-file
